{"is_source_file": false, "format": null, "description": null, "external_files": [], "external_methods": [], "published": [], "classes": [], "methods": [], "calls": [], "search-terms": [], "state": 2, "file_id": 4, "knowledge_revision": 16, "git_revision": "5df5c4bdda5fac2b4b78a43ef85c49e8fbf83d8a", "hash": "6c2104b8d219ed99234ae2d6329f4357", "format-version": 4, "code-base-name": "frontend_react", "filename": "frontend_react/src/index.css", "revision_history": [{"16": "5df5c4bdda5fac2b4b78a43ef85c49e8fbf83d8a"}]}